flatfilediff/__init__.py
flatfilediff/filediff.py
flatfilediff-0.0.2.dist-info/METADATA
flatfilediff-0.0.2.dist-info/WHEEL
flatfilediff-0.0.2.dist-info/top_level.txt
flatfilediff-0.0.2.dist-info/RECORD
